rapidquery-0.1.0a1.dist-info/METADATA
rapidquery-0.1.0a1.dist-info/WHEEL
rapidquery-0.1.0a1.dist-info/licenses/LICENSE
rapidquery/__init__.py
rapidquery/_lib.pyi
rapidquery/_lib.pypy311-pp73-darwin.so
rapidquery-0.1.0a1.dist-info/RECORD
