Metadata-Version: 2.4
Name: rapidquery
Version: 0.1.0a1
Classifier: Programming Language :: Python :: Implementation :: CPython
Classifier: Programming Language :: Python :: Implementation :: PyPy
Classifier: Programming Language :: Python :: 3 :: Only
Classifier: Programming Language :: Python :: 3.9
Classifier: Programming Language :: Python :: 3.10
Classifier: Programming Language :: Python :: 3.11
Classifier: Programming Language :: Python :: 3.12
Classifier: Programming Language :: Python :: 3.13
Classifier: Programming Language :: Python
Classifier: Programming Language :: Rust
Classifier: Intended Audience :: Developers
Classifier: Operating System :: POSIX :: Linux
Classifier: Operating System :: Microsoft :: Windows
Classifier: Operating System :: MacOS
Classifier: Typing :: Typed
License-File: LICENSE
Summary: RapiQuery is the fastest, full-feature, and easy-to-use Python SQL query builder written in Rust.
Keywords: SQL,dynamic-sql,sql-builder,rapidorm,seaql,pypika,orm,rapidquery
Home-Page: https://github.com/awolverp/rapidquery
Author-email: awolverp <awolverp@gmail.com>
License: GNU GPLv3
Requires-Python: >=3.8
Project-URL: Homepage, https://github.com/awolverp/rapidquery
